[
    {
        "key": "dbln",
        "value": "%7B%22100079017272283%22%3A%22lW9EiwoF%22%7D",
        "domain": "facebook.com",
        "path": "/login/device-based/",
        "hostOnly": false,
        "creation": "2025-10-06T14:56:28.155Z",
        "lastAccessed": "2025-10-06T14:56:28.155Z"
    },
    {
        "key": "sb",
        "value": "r1CxaDa6SPAhBE_UWW1LCD0e",
        "domain": "facebook.com",
        "path": "/",
        "hostOnly": false,
        "creation": "2025-10-06T14:56:28.155Z",
        "lastAccessed": "2025-10-06T14:56:28.155Z"
    },
    {
        "key": "ps_l",
        "value": "1",
        "domain": "facebook.com",
        "path": "/",
        "hostOnly": false,
        "creation": "2025-10-06T14:56:28.155Z",
        "lastAccessed": "2025-10-06T14:56:28.155Z"
    },
    {
        "key": "ps_n",
        "value": "1",
        "domain": "facebook.com",
        "path": "/",
        "hostOnly": false,
        "creation": "2025-10-06T14:56:28.155Z",
        "lastAccessed": "2025-10-06T14:56:28.155Z"
    },
    {
        "key": "datr",
        "value": "6SHQaKkQrgRMrUR17qbSUySB",
        "domain": "facebook.com",
        "path": "/",
        "hostOnly": false,
        "creation": "2025-10-06T14:56:28.155Z",
        "lastAccessed": "2025-10-06T14:56:28.155Z"
    },
    {
        "key": "dpr",
        "value": "2.2706050872802734",
        "domain": "facebook.com",
        "path": "/",
        "hostOnly": false,
        "creation": "2025-10-06T14:56:28.155Z",
        "lastAccessed": "2025-10-06T14:56:28.155Z"
    },
    {
        "key": "wd",
        "value": "809x1505",
        "domain": "facebook.com",
        "path": "/",
        "hostOnly": false,
        "creation": "2025-10-06T14:56:28.155Z",
        "lastAccessed": "2025-10-06T14:56:28.155Z"
    },
    {
        "key": "c_user",
        "value": "61581554446145",
        "domain": "facebook.com",
        "path": "/",
        "hostOnly": false,
        "creation": "2025-10-06T14:56:28.155Z",
        "lastAccessed": "2025-10-06T14:56:28.155Z"
    },
    {
        "key": "xs",
        "value": "27%3AG_AfvqNMNs9L-g%3A2%3A1759762148%3A-1%3A-1",
        "domain": "facebook.com",
        "path": "/",
        "hostOnly": false,
        "creation": "2025-10-06T14:56:28.156Z",
        "lastAccessed": "2025-10-06T14:56:28.156Z"
    },
    {
        "key": "fr",
        "value": "1vJgSeeWg7dPsmAGT.AWcnYCNroKeEerIykNSa7c5w0rBAUg0S97Zv_WI3WDeY6bF-abU.Bo49KC..AAA.0.0.Bo49b7.AWdSH-GNC0HTplp-l_4x7hoqJ2s",
        "domain": "facebook.com",
        "path": "/",
        "hostOnly": false,
        "creation": "2025-10-06T14:56:28.156Z",
        "lastAccessed": "2025-10-06T14:56:28.156Z"
    },
    {
        "key": "presence",
        "value": "C%7B%22t3%22%3A%5B%5D%2C%22utc3%22%3A1759762178554%2C%22v%22%3A1%7D",
        "domain": "facebook.com",
        "path": "/",
        "hostOnly": false,
        "creation": "2025-10-06T14:56:28.156Z",
        "lastAccessed": "2025-10-06T14:56:28.156Z"
    }
        ]
